LICENSE
MANIFEST.in
README.rst
setup.py
bootstrap/__init__.py
bootstrap/__main__.py
bootstrap/bootstrap.py
bootstrap/stuff.py
cmdline_bootstrap.egg-info/PKG-INFO
cmdline_bootstrap.egg-info/SOURCES.txt
cmdline_bootstrap.egg-info/dependency_links.txt
cmdline_bootstrap.egg-info/entry_points.txt
cmdline_bootstrap.egg-info/top_level.txt